[
  {
    "name": "7z",
    "path": "/7z",
    "description": "拥有极高压缩比的开源压缩软件。"
  },
  {
    "name": "ab",
    "path": "/ab",
    "description": "Apache服务器的性能测试工具"
  },
  {
    "name": "accept",
    "path": "/accept",
    "description": "指示打印系统接受发往指定目标打印机的打印任务"
  },
  {
    "name": "ack",
    "path": "/ack",
    "description": "比grep好用的文本搜索工具"
  },
  {
    "name": "ag",
    "path": "/ag",
    "description": "ack 的升级版，C语言编写，更快更人性化"
  },
  {
    "name": "alias",
    "path": "/alias",
    "description": "定义或显示别名。"
  },
  {
    "name": "apachectl",
    "path": "/apachectl",
    "description": "Apache服务器前端控制工具"
  },
  {
    "name": "apk",
    "path": "/apk",
    "description": "Alpine Linux 下的包管理工具"
  },
  {
    "name": "apropos",
    "path": "/apropos",
    "description": "在 whatis 数据库中查找字符串"
  },
  {
    "name": "apt-get",
    "path": "/apt-get",
    "description": "Debian Linux发行版中的APT软件包管理工具"
  },
  {
    "name": "apt-key",
    "path": "/apt-key",
    "description": "管理Debian Linux系统中的软件包密钥"
  },
  {
    "name": "apt-sortpkgs",
    "path": "/apt-sortpkgs",
    "description": "Debian Linux下对软件包索引文件进行排序的工具"
  },
  {
    "name": "aptitude",
    "path": "/aptitude",
    "description": "Debian Linux系统中软件包管理工具"
  },
  {
    "name": "ar",
    "path": "/ar",
    "description": "建立或修改备存文件，或是从备存文件中抽取文件"
  },
  {
    "name": "arch",
    "path": "/arch",
    "description": "显示当前主机的硬件架构类型"
  },
  {
    "name": "arj",
    "path": "/arj",
    "description": "用于创建和管理.arj压缩包"
  },
  {
    "name": "arp",
    "path": "/arp",
    "description": "arp 命令用于显示和修改 IP 到 MAC 转换表"
  },
  {
    "name": "arpd",
    "path": "/arpd",
    "description": "收集免费ARP信息"
  },
  {
    "name": "arping",
    "path": "/arping",
    "description": "通过发送ARP协议报文测试网络"
  },
  {
    "name": "arptables",
    "path": "/arptables",
    "description": "管理ARP包过滤规则表"
  },
  {
    "name": "arpwatch",
    "path": "/arpwatch",
    "description": "监听网络上ARP的记录"
  },
  {
    "name": "as",
    "path": "/as",
    "description": "汇编语言编译器"
  },
  {
    "name": "at",
    "path": "/at",
    "description": "在指定时间执行一个任务"
  },
  {
    "name": "atop",
    "path": "/atop",
    "description": "监控Linux系统资源与进程的工具"
  },
  {
    "name": "atq",
    "path": "/atq",
    "description": "列出当前用户的at任务列表"
  },
  {
    "name": "atrm",
    "path": "/atrm",
    "description": "删除待执行任务队列中的指定任务"
  },
  {
    "name": "awk",
    "path": "/awk",
    "description": "文本和数据进行处理的编程语言"
  },
  {
    "name": "axel",
    "path": "/axel",
    "description": "多线程下载工具"
  },
  {
    "name": "badblocks",
    "path": "/badblocks",
    "description": "查找磁盘中损坏的区块"
  },
  {
    "name": "base64",
    "path": "/base64",
    "description": "base64 编码/解码文件或标准输入输出"
  },
  {
    "name": "basename",
    "path": "/basename",
    "description": "打印目录或者文件的基本名称"
  },
  {
    "name": "batch",
    "path": "/batch",
    "description": "在系统不繁忙的时候执行定时任务"
  },
  {
    "name": "bc",
    "path": "/bc",
    "description": "算术操作精密运算工具"
  },
  {
    "name": "beep",
    "path": "/beep",
    "description": "用于控制 PC 扬声器发出蜂鸣声的命令行工具。"
  },
  {
    "name": "bg",
    "path": "/bg",
    "description": "将前台终端作业移动到后台运行"
  },
  {
    "name": "bind",
    "path": "/bind",
    "description": "显示或设置键盘按键与其相关的功能"
  },
  {
    "name": "blkid",
    "path": "/blkid",
    "description": "查看块设备的文件系统类型、LABEL、UUID等信息"
  },
  {
    "name": "blockdev",
    "path": "/blockdev",
    "description": "从命令行调用区块设备控制程序"
  },
  {
    "name": "break",
    "path": "/break",
    "description": "结束for，while或until循环。"
  },
  {
    "name": "builtin",
    "path": "/builtin",
    "description": "执行bash内建命令。"
  },
  {
    "name": "bunzip2",
    "path": "/bunzip2",
    "description": "可解压缩.bz2格式的压缩文件。 "
  },
  {
    "name": "bye",
    "path": "/bye",
    "description": "命令用于中断FTP连线并结束程序"
  },
  {
    "name": "bzcat",
    "path": "/bzcat",
    "description": "不解压，直接查看指定的.bz2文件"
  },
  {
    "name": "bzcmp",
    "path": "/bzcmp",
    "description": "比较两个压缩包中的文件"
  },
  {
    "name": "bzdiff",
    "path": "/bzdiff",
    "description": "直接比较两个.bz2压缩包中文件的不同"
  },
  {
    "name": "bzgrep",
    "path": "/bzgrep",
    "description": "使用正则表达式搜索.bz2压缩包中文件"
  },
  {
    "name": "bzip2",
    "path": "/bzip2",
    "description": "将文件压缩成bz2格式"
  },
  {
    "name": "bzip2recover",
    "path": "/bzip2recover",
    "description": "恢复被破坏的.bz2压缩包中的文件"
  },
  {
    "name": "bzless",
    "path": "/bzless",
    "description": "增强.bz2压缩包查看器"
  },
  {
    "name": "bzmore",
    "path": "/bzmore",
    "description": "查看bzip2压缩过的文本文件的内容"
  },
  {
    "name": "cal",
    "path": "/cal",
    "description": "显示当前日历或指定日期的日历"
  },
  {
    "name": "cancel",
    "path": "/cancel",
    "description": "取消已存在的打印任务"
  },
  {
    "name": "cat",
    "path": "/cat",
    "description": "连接多个文件并打印到标准输出。"
  },
  {
    "name": "cd",
    "path": "/cd",
    "description": "切换用户当前工作目录。"
  },
  {
    "name": "cdrecord",
    "path": "/cdrecord",
    "description": "Linux系统下光盘刻录功能命令"
  },
  {
    "name": "chage",
    "path": "/chage",
    "description": "修改帐号和密码的有效期限"
  },
  {
    "name": "chattr",
    "path": "/chattr",
    "description": "用来改变文件属性"
  },
  {
    "name": "chcon",
    "path": "/chcon",
    "description": "修改对象（文件）的安全上下文"
  },
  {
    "name": "chfn",
    "path": "/chfn",
    "description": "用来改变finger命令显示的信息"
  },
  {
    "name": "chgrp",
    "path": "/chgrp",
    "description": "用来变更文件或目录的所属群组"
  },
  {
    "name": "chkconfig",
    "path": "/chkconfig",
    "description": "检查或设置系统的各种服务"
  },
  {
    "name": "chmod",
    "path": "/chmod",
    "description": "用来变更文件或目录的权限"
  },
  {
    "name": "chown",
    "path": "/chown",
    "description": "用来变更文件或目录的拥有者或所属群组"
  },
  {
    "name": "chpasswd",
    "path": "/chpasswd",
    "description": "批量更新用户口令的工具"
  },
  {
    "name": "chroot",
    "path": "/chroot",
    "description": "把根目录换成指定的目的目录"
  },
  {
    "name": "chsh",
    "path": "/chsh",
    "description": "用来更换登录系统时使用的shell"
  },
  {
    "name": "cksum",
    "path": "/cksum",
    "description": "检查文件的CRC是否正确"
  },
  {
    "name": "clear",
    "path": "/clear",
    "description": "清除当前屏幕终端上的任何信息"
  },
  {
    "name": "clock",
    "path": "/clock",
    "description": "用于调整 RTC 时间"
  },
  {
    "name": "clockdiff",
    "path": "/clockdiff",
    "description": "检测两台linux主机的时间差"
  },
  {
    "name": "cmp",
    "path": "/cmp",
    "description": "比较两个文件是否有差异"
  },
  {
    "name": "col",
    "path": "/col",
    "description": "过滤控制字符"
  },
  {
    "name": "colrm",
    "path": "/colrm",
    "description": "删除文件中的指定列"
  },
  {
    "name": "column",
    "path": "/column",
    "description": "按列格式化输出文件"
  },
  {
    "name": "comm",
    "path": "/comm",
    "description": "按行比较两个已排序的文件。"
  },
  {
    "name": "command",
    "path": "/command",
    "description": "调用并执行指定的命令"
  },
  {
    "name": "compress",
    "path": "/compress",
    "description": "使用Lempress-Ziv编码压缩数据文件"
  },
  {
    "name": "consoletype",
    "path": "/consoletype",
    "description": "输出已连接的终端类型"
  },
  {
    "name": "continue",
    "path": "/continue",
    "description": "结束本次循环，继续执行下一个for，while或until循环。"
  },
  {
    "name": "convertquota",
    "path": "/convertquota",
    "description": "把老的配额文件转换为新的格式"
  },
  {
    "name": "cp",
    "path": "/cp",
    "description": "将源文件或目录复制到目标文件或目录中"
  },
  {
    "name": "cpio",
    "path": "/cpio",
    "description": "用来建立、还原备份档的工具程序"
  },
  {
    "name": "createrepo",
    "path": "/createrepo",
    "description": "创建YUM仓库"
  },
  {
    "name": "crontab",
    "path": "/crontab",
    "description": "提交和管理用户的需要周期性执行的任务"
  },
  {
    "name": "csplit",
    "path": "/csplit",
    "description": "将一个大文件分割成小的碎片文件"
  },
  {
    "name": "cu",
    "path": "/cu",
    "description": "用于连接另一个系统主机"
  },
  {
    "name": "cupsdisable",
    "path": "/cupsdisable",
    "description": "停止指定的打印机"
  },
  {
    "name": "cupsenable",
    "path": "/cupsenable",
    "description": "启动指定的打印机"
  },
  {
    "name": "curl",
    "path": "/curl",
    "description": "利用URL规则在命令行下工作的文件传输工具"
  },
  {
    "name": "cut",
    "path": "/cut",
    "description": "连接文件并打印到标准输出设备上"
  },
  {
    "name": "date",
    "path": "/date",
    "description": "显示或设置系统时间与日期"
  },
  {
    "name": "dc",
    "path": "/dc",
    "description": "任意精度计算器"
  },
  {
    "name": "dd",
    "path": "/dd",
    "description": "复制文件并对原文件的内容进行转换和格式化处理"
  },
  {
    "name": "declare",
    "path": "/declare",
    "description": "声明变量，设置或显示变量的值和属性。"
  },
  {
    "name": "depmod",
    "path": "/depmod",
    "description": "分析可载入模块的相依性"
  },
  {
    "name": "df",
    "path": "/df",
    "description": "显示磁盘的相关信息"
  },
  {
    "name": "dhclient",
    "path": "/dhclient",
    "description": "动态获取或释放IP地址"
  },
  {
    "name": "dhcpd",
    "path": "/dhcpd",
    "description": "运行DHCP服务器"
  },
  {
    "name": "dhcrelay",
    "path": "/dhcrelay",
    "description": "使用dhcrelay命令可以提供中继DHCP和BOOTP请求"
  },
  {
    "name": "diff",
    "path": "/diff",
    "description": "比较给定的两个文件的不同"
  },
  {
    "name": "diff3",
    "path": "/diff3",
    "description": "比较3个文件不同的地方"
  },
  {
    "name": "diffstat",
    "path": "/diffstat",
    "description": "显示diff命令输出信息的柱状图"
  },
  {
    "name": "dig",
    "path": "/dig",
    "description": "域名查询工具"
  },
  {
    "name": "dircolors",
    "path": "/dircolors",
    "description": "置ls命令在显示目录或文件时所用的色彩"
  },
  {
    "name": "dirname",
    "path": "/dirname",
    "description": "去除文件名中的非目录部分"
  },
  {
    "name": "dirs",
    "path": "/dirs",
    "description": "显示目录堆栈。"
  },
  {
    "name": "disown",
    "path": "/disown",
    "description": "从当前的shell中移除作业。"
  },
  {
    "name": "dmesg",
    "path": "/dmesg",
    "description": "显示Linux系统启动信息"
  },
  {
    "name": "dmidecode",
    "path": "/dmidecode",
    "description": "在Linux系统下获取有关硬件方面的信息"
  },
  {
    "name": "dnf",
    "path": "/dnf",
    "description": "新一代的RPM软件包管理器"
  },
  {
    "name": "dnsdomainname",
    "path": "/dnsdomainname",
    "description": "定义DNS系统中FQDN名称的域名"
  },
  {
    "name": "docker",
    "path": "/docker",
    "description": "容器化技术，可以将应用程序及其依赖项打包到一个可移植的容器中，使其可以在不同的环境中运行"
  },
  {
    "name": "domainname",
    "path": "/domainname",
    "description": "显示和设置系统的NIS域名"
  },
  {
    "name": "dos2unix",
    "path": "/dos2unix",
    "description": "将DOS格式文本文件转换成Unix格式"
  },
  {
    "name": "dpkg-deb",
    "path": "/dpkg-deb",
    "description": "Debian Linux下的软件包管理工具"
  },
  {
    "name": "dpkg-divert",
    "path": "/dpkg-divert",
    "description": "Debian Linux中创建并管理一个转向列表"
  },
  {
    "name": "dpkg-preconfigure",
    "path": "/dpkg-preconfigure",
    "description": "Debian Linux中软件包安装之前询问问题"
  },
  {
    "name": "dpkg-query",
    "path": "/dpkg-query",
    "description": "Debian Linux中软件包的查询工具"
  },
  {
    "name": "dpkg-reconfigure",
    "path": "/dpkg-reconfigure",
    "description": "Debian Linux中重新配制一个已经安装的软件包"
  },
  {
    "name": "dpkg-split",
    "path": "/dpkg-split",
    "description": "Debian Linux中将大软件包分割成小包"
  },
  {
    "name": "dpkg-statoverride",
    "path": "/dpkg-statoverride",
    "description": "Debian Linux中覆盖文件的所有权和模式"
  },
  {
    "name": "dpkg-trigger",
    "path": "/dpkg-trigger",
    "description": "Debian Linux下的软件包触发器"
  },
  {
    "name": "dpkg",
    "path": "/dpkg",
    "description": "Debian Linux系统上安装、创建和管理软件包"
  },
  {
    "name": "dris",
    "path": "/dris",
    "description": "显示和清空目录堆栈中的内容"
  },
  {
    "name": "dstat",
    "path": "/dstat",
    "description": "通用的系统资源统计工具"
  },
  {
    "name": "du",
    "path": "/du",
    "description": "显示每个文件和目录的磁盘使用空间"
  },
  {
    "name": "dump",
    "path": "/dump",
    "description": "用于备份ext2或者ext3文件系统"
  },
  {
    "name": "e2fsck",
    "path": "/e2fsck",
    "description": "用于检查第二扩展文件系统的完整性"
  },
  {
    "name": "e2label",
    "path": "/e2label",
    "description": "设置第二扩展文件系统的卷标"
  },
  {
    "name": "echo",
    "path": "/echo",
    "description": "输出指定的字符串或者变量"
  },
  {
    "name": "ed",
    "path": "/ed",
    "description": "单行纯文本编辑器"
  },
  {
    "name": "edquota",
    "path": "/edquota",
    "description": "用于编辑指定用户或工作组磁盘配额"
  },
  {
    "name": "egrep",
    "path": "/egrep",
    "description": "在文件内查找指定的字符串"
  },
  {
    "name": "eject",
    "path": "/eject",
    "description": "用来退出抽取式设备"
  },
  {
    "name": "elinks",
    "path": "/elinks",
    "description": "纯文本界面的WWW浏览器"
  },
  {
    "name": "elm",
    "path": "/elm",
    "description": "纯文本邮件客户端程序"
  },
  {
    "name": "emacs",
    "path": "/emacs",
    "description": "功能强大的全屏文本编辑器"
  },
  {
    "name": "enable",
    "path": "/enable",
    "description": "启动或禁用shell内建命令"
  },
  {
    "name": "env",
    "path": "/env",
    "description": "显示系统中已存在的环境变量"
  },
  {
    "name": "ethtool",
    "path": "/ethtool",
    "description": "显示或修改以太网卡的配置信息"
  },
  {
    "name": "ex",
    "path": "/ex",
    "description": "启动vim编辑器的ex编辑模式"
  },
  {
    "name": "exec",
    "path": "/exec",
    "description": "调用并执行指定的命令"
  },
  {
    "name": "exit",
    "path": "/exit",
    "description": "退出当前的shell。"
  },
  {
    "name": "expand",
    "path": "/expand",
    "description": "将文件的制表符转换为空白字符"
  },
  {
    "name": "export",
    "path": "/export",
    "description": "为shell变量或函数设置导出属性。"
  },
  {
    "name": "exportfs",
    "path": "/exportfs",
    "description": "管理NFS共享文件系统列表"
  },
  {
    "name": "expr",
    "path": "/expr",
    "description": "一款表达式计算工具"
  },
  {
    "name": "false",
    "path": "/false",
    "description": "返回状态为失败。"
  },
  {
    "name": "fc",
    "path": "/fc",
    "description": "显示历史列表中的命令或修改指定的历史命令并执行。"
  },
  {
    "name": "fdisk",
    "path": "/fdisk",
    "description": "查看磁盘使用情况和磁盘分区"
  },
  {
    "name": "fg",
    "path": "/fg",
    "description": "将后台作业移动到前台终端运行"
  },
  {
    "name": "fgrep",
    "path": "/fgrep",
    "description": "为文件搜索文字字符串"
  },
  {
    "name": "figlet",
    "path": "/figlet",
    "description": "字符串转为 “字画符”。"
  },
  {
    "name": "file",
    "path": "/file",
    "description": "用来探测给定文件的类型"
  },
  {
    "name": "find",
    "path": "/find",
    "description": "在指定目录下查找文件"
  },
  {
    "name": "findfs",
    "path": "/findfs",
    "description": "标签或UUID查找文件系统"
  },
  {
    "name": "finger",
    "path": "/finger",
    "description": "用于查找并显示用户信息"
  },
  {
    "name": "firewall-cmd",
    "path": "/firewall-cmd",
    "description": "Linux上新用的防火墙软件，跟iptables差不多的工具"
  },
  {
    "name": "fishshell",
    "path": "/fishshell",
    "description": "比 bash 更好用的 shell"
  },
  {
    "name": "fmt",
    "path": "/fmt",
    "description": "读取文件后优化处理并输出"
  },
  {
    "name": "fold",
    "path": "/fold",
    "description": "控制文件内容输出时所占用的屏幕宽度"
  },
  {
    "name": "fping",
    "path": "/fping",
    "description": "fping检测主机是否存在"
  },
  {
    "name": "free",
    "path": "/free",
    "description": "显示内存的使用情况"
  },
  {
    "name": "fsck",
    "path": "/fsck",
    "description": "fsck（英文全拼：file system check）命令检查并且试图修复文件系统中的错误"
  },
  {
    "name": "ftp",
    "path": "/ftp",
    "description": "用来设置文件系统相关功能"
  },
  {
    "name": "ftpcount",
    "path": "/ftpcount",
    "description": "显示目前已FTP登入的用户人数"
  },
  {
    "name": "ftpshut",
    "path": "/ftpshut",
    "description": "在指定的时间关闭FTP服务器"
  },
  {
    "name": "ftptop",
    "path": "/ftptop",
    "description": "proftpd服务器的连接状态"
  },
  {
    "name": "ftpwho",
    "path": "/ftpwho",
    "description": "显示当前每个ftp会话信息"
  },
  {
    "name": "fuser",
    "path": "/fuser",
    "description": "使用文件或文件结构识别进程"
  },
  {
    "name": "gcc",
    "path": "/gcc",
    "description": "基于C/C++的编译器"
  },
  {
    "name": "gcov",
    "path": "/gcov",
    "description": "测试程序的代码覆盖率的工具"
  },
  {
    "name": "gdb",
    "path": "/gdb",
    "description": "功能强大的程序调试器"
  },
  {
    "name": "get_module",
    "path": "/get_module",
    "description": "获取Linux内核模块的详细信息"
  },
  {
    "name": "getcap",
    "path": "/getcap",
    "description": "显示文件的能力（capabilities）"
  },
  {
    "name": "getenforce",
    "path": "/getenforce",
    "description": "显示当前SELinux的应用模式，是强制、执行还是停用"
  },
  {
    "name": "getent",
    "path": "/getent",
    "description": "查询 DNS 名称服务器中的命名空间"
  },
  {
    "name": "getfacl",
    "path": "/getfacl",
    "description": "获取文件访问控制列表(access control lists)"
  },
  {
    "name": "getsebool",
    "path": "/getsebool",
    "description": "查询SElinux策略内各项规则的布尔值"
  },
  {
    "name": "git",
    "path": "/git",
    "description": "是目前世界上最先进的分布式版本控制系统"
  },
  {
    "name": "gpasswd",
    "path": "/gpasswd",
    "description": "Linux下工作组文件的管理工具"
  },
  {
    "name": "gpg",
    "path": "/gpg",
    "description": "可用于签名、检查、加密或解密的工具"
  },
  {
    "name": "gpm",
    "path": "/gpm",
    "description": "提供文字模式下的滑鼠事件处理"
  },
  {
    "name": "grep",
    "path": "/grep",
    "description": "强大的文本搜索工具"
  },
  {
    "name": "groupadd",
    "path": "/groupadd",
    "description": "用于创建一个新的工作组"
  },
  {
    "name": "groupdel",
    "path": "/groupdel",
    "description": "用于删除指定的工作组"
  },
  {
    "name": "groupmems",
    "path": "/groupmems",
    "description": "管理用户主要组的成员"
  },
  {
    "name": "groupmod",
    "path": "/groupmod",
    "description": "修改系统上的组定义"
  },
  {
    "name": "groups",
    "path": "/groups",
    "description": "打印指定用户所在组的名称。"
  },
  {
    "name": "grpck",
    "path": "/grpck",
    "description": "用于验证组文件的完整性"
  },
  {
    "name": "grpconv",
    "path": "/grpconv",
    "description": "用来开启群组的投影密码"
  },
  {
    "name": "grpunconv",
    "path": "/grpunconv",
    "description": "用来关闭群组的投影密码"
  },
  {
    "name": "grub",
    "path": "/grub",
    "description": "多重引导程序grub的命令行shell工具"
  },
  {
    "name": "grub2-mkconfig",
    "path": "/grub2-mkconfig",
    "description": "生成 grub.cfg 配置文件。"
  },
  {
    "name": "grub2-set-default",
    "path": "/grub2-set-default",
    "description": "设置系统默认的启动内核"
  },
  {
    "name": "gunzip",
    "path": "/gunzip",
    "description": "用来解压缩文件"
  },
  {
    "name": "gzexe",
    "path": "/gzexe",
    "description": "用来压缩可执行文件"
  },
  {
    "name": "gzip",
    "path": "/gzip",
    "description": "用来压缩文件"
  },
  {
    "name": "halt",
    "path": "/halt",
    "description": "关闭正在运行的Linux操作系统"
  },
  {
    "name": "hcitool",
    "path": "/hcitool",
    "description": "hcitool是一个Linux命令行工具，用于管理和调试蓝牙设备。它可以用于扫描周围的蓝牙设备、连接到蓝牙设备发送命令和数据包等。"
  },
  {
    "name": "hdparm",
    "path": "/hdparm",
    "description": "显示与设定硬盘的参数"
  },
  {
    "name": "head",
    "path": "/head",
    "description": "显示文件的开头部分。"
  },
  {
    "name": "help",
    "path": "/help",
    "description": "该命令是bash内建命令，用于显示bash内建命令的帮助信息。"
  },
  {
    "name": "hexdump",
    "path": "/hexdump",
    "description": "显示文件十六进制格式"
  },
  {
    "name": "history",
    "path": "/history",
    "description": "显示或操作历史列表。"
  },
  {
    "name": "host",
    "path": "/host",
    "description": "常用的分析域名查询工具"
  },
  {
    "name": "hostid",
    "path": "/hostid",
    "description": "显示当前主机的十六进制数字标识。"
  },
  {
    "name": "hostname",
    "path": "/hostname",
    "description": "显示和设置系统的主机名"
  },
  {
    "name": "hostnamectl",
    "path": "/hostnamectl",
    "description": "查询或更改系统主机名"
  },
  {
    "name": "hping3",
    "path": "/hping3",
    "description": "测试网络及主机的安全"
  },
  {
    "name": "htdigest",
    "path": "/htdigest",
    "description": "Apache服务器内置工具"
  },
  {
    "name": "htop",
    "path": "/htop",
    "description": "[非内部命令]一个互动的进程查看器，可以动态观察系统进程状况"
  },
  {
    "name": "htpasswd",
    "path": "/htpasswd",
    "description": "apache服务器创建密码认证文件"
  },
  {
    "name": "hwclock",
    "path": "/hwclock",
    "description": "显示与设定硬件时钟"
  },
  {
    "name": "iconv",
    "path": "/iconv",
    "description": "转换文件的编码方式"
  },
  {
    "name": "id",
    "path": "/id",
    "description": "打印真实以及有效的用户和所在组的信息"
  },
  {
    "name": "ifcfg",
    "path": "/ifcfg",
    "description": "置Linux中的网络接口参数"
  },
  {
    "name": "ifconfig",
    "path": "/ifconfig",
    "description": "配置和显示Linux系统网卡的网络参数"
  },
  {
    "name": "ifdown",
    "path": "/ifdown",
    "description": "禁用指定的网络接口"
  },
  {
    "name": "ifstat",
    "path": "/ifstat",
    "description": "统计网络接口流量状态"
  },
  {
    "name": "iftop",
    "path": "/iftop",
    "description": "一款实时流量监控工具"
  },
  {
    "name": "ifup",
    "path": "/ifup",
    "description": "激活指定的网络接口"
  },
  {
    "name": "indent",
    "path": "/indent",
    "description": "格式化C语言的源文件"
  },
  {
    "name": "info",
    "path": "/info",
    "description": "Linux下info格式的帮助指令"
  },
  {
    "name": "init",
    "path": "/init",
    "description": "init进程是所有Linux进程的父进程"
  },
  {
    "name": "inotifywait",
    "path": "/inotifywait",
    "description": "异步文件系统监控机制"
  },
  {
    "name": "insmod",
    "path": "/insmod",
    "description": "将给定的模块加载到内核中"
  },
  {
    "name": "install",
    "path": "/install",
    "description": "安装或升级软件或备份数据"
  },
  {
    "name": "iostat",
    "path": "/iostat",
    "description": "监视系统输入输出设备和CPU的使用情况"
  },
  {
    "name": "iotop",
    "path": "/iotop",
    "description": "用来监视磁盘I/O使用状况的工具"
  },
  {
    "name": "ip",
    "path": "/ip",
    "description": "网络配置工具"
  },
  {
    "name": "ip6tables-restore",
    "path": "/ip6tables-restore",
    "description": "还原ip6tables表"
  },
  {
    "name": "ip6tables-save",
    "path": "/ip6tables-save",
    "description": "保存ip6tables表配置"
  },
  {
    "name": "ip6tables",
    "path": "/ip6tables",
    "description": "linux中防火墙软件"
  },
  {
    "name": "ipcalc",
    "path": "/ipcalc",
    "description": "简单的IP地址计算器"
  },
  {
    "name": "ipcrm",
    "path": "/ipcrm",
    "description": "删除消息队列、信号集、或者共享内存标识"
  },
  {
    "name": "ipcs",
    "path": "/ipcs",
    "description": "分析消息队列共享内存和信号量"
  },
  {
    "name": "iperf",
    "path": "/iperf",
    "description": "网络性能测试工具"
  },
  {
    "name": "iptables-restore",
    "path": "/iptables-restore",
    "description": "还原iptables表的配置"
  },
  {
    "name": "iptables-save",
    "path": "/iptables-save",
    "description": "备份iptables的表配置"
  },
  {
    "name": "iptables",
    "path": "/iptables",
    "description": "Linux上常用的防火墙软件"
  },
  {
    "name": "iptraf",
    "path": "/iptraf",
    "description": "实时地监视网卡流量"
  },
  {
    "name": "iptstate",
    "path": "/iptstate",
    "description": "显示iptables的工作状态"
  },
  {
    "name": "iscsiadm",
    "path": "/iscsiadm",
    "description": "管理iSCSI连接"
  },
  {
    "name": "ispell",
    "path": "/ispell",
    "description": "检查文件中出现的拼写错误"
  },
  {
    "name": "jed",
    "path": "/jed",
    "description": "主要用于编辑代码的编辑器"
  },
  {
    "name": "jobs",
    "path": "/jobs",
    "description": "显示作业的状态。"
  },
  {
    "name": "joe",
    "path": "/joe",
    "description": "强大的纯文本编辑器"
  },
  {
    "name": "join",
    "path": "/join",
    "description": "两个文件中指定栏位内容相同的行连接起来"
  },
  {
    "name": "journalctl",
    "path": "/journalctl",
    "description": "检索 systemd 日志，只要使用 systemd 的 Linux 发行版（如 Fedora、Ubuntu Modern、Debian、SUSE、Arch），几乎都会配备 journalctl。"
  },
  {
    "name": "jq",
    "path": "/jq",
    "description": "一个灵活的轻量级命令行JSON处理器"
  },
  {
    "name": "jwhois",
    "path": "/jwhois",
    "description": "whois 客户端服务"
  },
  {
    "name": "kernelversion",
    "path": "/kernelversion",
    "description": "打印当前内核的主版本号"
  },
  {
    "name": "kexec",
    "path": "/kexec",
    "description": "从当前正在运行的内核引导到一个新内核"
  },
  {
    "name": "kill",
    "path": "/kill",
    "description": "发送信号到进程。"
  },
  {
    "name": "killall",
    "path": "/killall",
    "description": "使用进程的名称来杀死一组进程"
  },
  {
    "name": "last",
    "path": "/last",
    "description": "列出目前与过去登入系统的用户相关信息"
  },
  {
    "name": "lastb",
    "path": "/lastb",
    "description": "列出登入系统失败的用户相关信息"
  },
  {
    "name": "lastlog",
    "path": "/lastlog",
    "description": "显示系统中所有用户最近一次登录信息"
  },
  {
    "name": "ld",
    "path": "/ld",
    "description": "将目标文件连接为可执行程序"
  },
  {
    "name": "ldconfig",
    "path": "/ldconfig",
    "description": "动态链接库管理命令"
  },
  {
    "name": "ldd",
    "path": "/ldd",
    "description": "打印程序或者库文件所依赖的共享库列表"
  },
  {
    "name": "less",
    "path": "/less",
    "description": "分屏上下翻页浏览文件内容"
  },
  {
    "name": "let",
    "path": "/let",
    "description": "简单的计算器，执行算术表达式。"
  },
  {
    "name": "lftp",
    "path": "/lftp",
    "description": "优秀的文件客户端程序"
  },
  {
    "name": "lftpget",
    "path": "/lftpget",
    "description": "调用lftp指令下载指定的文件"
  },
  {
    "name": "lha",
    "path": "/lha",
    "description": "压缩或解压缩lzh格式文件"
  },
  {
    "name": "lilo",
    "path": "/lilo",
    "description": "安装核心载入开机管理程序"
  },
  {
    "name": "ln",
    "path": "/ln",
    "description": "用来为文件创建链接"
  },
  {
    "name": "lnstat",
    "path": "/lnstat",
    "description": "显示Linux系统的网路状态"
  },
  {
    "name": "local",
    "path": "/local",
    "description": "在函数内定义局部变量。"
  },
  {
    "name": "locate",
    "path": "/locate",
    "description": "比 find 好用的文件查找工具"
  },
  {
    "name": "logger",
    "path": "/logger",
    "description": "在系统日志中记录相应条目"
  },
  {
    "name": "login",
    "path": "/login",
    "description": "登录系统或切换用户身份"
  },
  {
    "name": "logname",
    "path": "/logname",
    "description": "打印当前终端登录用户的名称。"
  },
  {
    "name": "logout",
    "path": "/logout",
    "description": "退出当前登录的Shell"
  },
  {
    "name": "logrotate",
    "path": "/logrotate",
    "description": "系统日志进行轮转、压缩和删除"
  },
  {
    "name": "logsave",
    "path": "/logsave",
    "description": "将命令的输出信息保存到指定的日志文件"
  },
  {
    "name": "logwatch",
    "path": "/logwatch",
    "description": "可定制和可插入式的日志监视系统"
  },
  {
    "name": "look",
    "path": "/look",
    "description": "显示文件中以指定字符串开头的任意行"
  },
  {
    "name": "losetup",
    "path": "/losetup",
    "description": "设定与控制循环（loop）设备"
  },
  {
    "name": "lp",
    "path": "/lp",
    "description": "打印文件或修改排队的打印任务"
  },
  {
    "name": "lpadmin",
    "path": "/lpadmin",
    "description": "配置CUPS套件中的打印机和类"
  },
  {
    "name": "lpc",
    "path": "/lpc",
    "description": "命令行方式打印机控制程序"
  },
  {
    "name": "lpq",
    "path": "/lpq",
    "description": "显示打印队列中的打印任务的状态信息"
  },
  {
    "name": "lpr",
    "path": "/lpr",
    "description": "将文件发送给指定打印机进行打印"
  },
  {
    "name": "lprm",
    "path": "/lprm",
    "description": "删除打印队列中的打印任务"
  },
  {
    "name": "lpstat",
    "path": "/lpstat",
    "description": "显示CUPS中打印机的状态信息"
  },
  {
    "name": "ls",
    "path": "/ls",
    "description": "显示目录内容列表"
  },
  {
    "name": "lsattr",
    "path": "/lsattr",
    "description": "查看文件的第二扩展文件系统属性"
  },
  {
    "name": "lsb_release",
    "path": "/lsb_release",
    "description": "显示发行版本信息"
  },
  {
    "name": "lsblk",
    "path": "/lsblk",
    "description": "列出块设备信息"
  },
  {
    "name": "lscpu",
    "path": "/lscpu",
    "description": "显示有关CPU架构的信息"
  },
  {
    "name": "lsmod",
    "path": "/lsmod",
    "description": "显示已载入系统的模块"
  },
  {
    "name": "lsof",
    "path": "/lsof",
    "description": "显示Linux系统当前已打开的所有文件列表 `lsof -p pid`"
  },
  {
    "name": "lspci",
    "path": "/lspci",
    "description": "显示当前主机的所有PCI总线信息"
  },
  {
    "name": "lsusb",
    "path": "/lsusb",
    "description": "显示本机的USB设备列表信息"
  },
  {
    "name": "ltrace",
    "path": "/ltrace",
    "description": "用来跟踪进程调用库函数的情况"
  },
  {
    "name": "lvcreate",
    "path": "/lvcreate",
    "description": "用于创建LVM的逻辑卷"
  },
  {
    "name": "lvdisplay",
    "path": "/lvdisplay",
    "description": "显示逻辑卷属性"
  },
  {
    "name": "lvextend",
    "path": "/lvextend",
    "description": "扩展逻辑卷空间"
  },
  {
    "name": "lvreduce",
    "path": "/lvreduce",
    "description": "收缩逻辑卷空间"
  },
  {
    "name": "lvremove",
    "path": "/lvremove",
    "description": "删除指定LVM逻辑卷"
  },
  {
    "name": "lvresize",
    "path": "/lvresize",
    "description": "调整逻辑卷空间大小"
  },
  {
    "name": "lvscan",
    "path": "/lvscan",
    "description": "扫描逻辑卷"
  },
  {
    "name": "lynx",
    "path": "/lynx",
    "description": "纯文本模式的网页浏览器"
  },
  {
    "name": "mail",
    "path": "/mail",
    "description": "命令行下发送和接收电子邮件"
  },
  {
    "name": "mailq",
    "path": "/mailq",
    "description": "显示待发送的邮件队列"
  },
  {
    "name": "mailstat",
    "path": "/mailstat",
    "description": "显示到达的邮件状态"
  },
  {
    "name": "make",
    "path": "/make",
    "description": "GNU的工程化编译工具"
  },
  {
    "name": "man",
    "path": "/man",
    "description": "查看Linux中的指令帮助"
  },
  {
    "name": "mapfile",
    "path": "/mapfile",
    "description": "从标准输入读取行并赋值到数组。"
  },
  {
    "name": "md5sum",
    "path": "/md5sum",
    "description": "计算和校验文件报文摘要的工具程序"
  },
  {
    "name": "mesg",
    "path": "/mesg",
    "description": "设置当前终端的写权限"
  },
  {
    "name": "mii-tool",
    "path": "/mii-tool",
    "description": "配置网络设备协商方式的工具"
  },
  {
    "name": "mkbootdisk",
    "path": "/mkbootdisk",
    "description": "可建立目前系统的启动盘"
  },
  {
    "name": "mkcert",
    "path": "/mkcert",
    "description": "用来生成自签证书的工具"
  },
  {
    "name": "mkdir",
    "path": "/mkdir",
    "description": "用来创建目录"
  },
  {
    "name": "mke2fs",
    "path": "/mke2fs",
    "description": "创建磁盘分区上的“etc2/etc3”文件系统"
  },
  {
    "name": "mkfs",
    "path": "/mkfs",
    "description": "用于在设备上创建Linux文件系统"
  },
  {
    "name": "mkinitrd",
    "path": "/mkinitrd",
    "description": "建立要载入ramdisk的映像文件"
  },
  {
    "name": "mkisofs",
    "path": "/mkisofs",
    "description": "建立ISO 9660映像文件"
  },
  {
    "name": "mknod",
    "path": "/mknod",
    "description": "创建字符设备文件和块设备文件"
  },
  {
    "name": "mkswap",
    "path": "/mkswap",
    "description": "建立和设置SWAP交换分区"
  },
  {
    "name": "mktemp",
    "path": "/mktemp",
    "description": "创建临时文件供shell脚本使用"
  },
  {
    "name": "modetest",
    "path": "/modetest",
    "description": "DRM/KMS驱动程序libdrm中的模式测试工具"
  },
  {
    "name": "modinfo",
    "path": "/modinfo",
    "description": "显示给定模块的详细信息"
  },
  {
    "name": "modprobe",
    "path": "/modprobe",
    "description": "自动处理可载入模块"
  },
  {
    "name": "more",
    "path": "/more",
    "description": "显示文件内容，每次显示一屏"
  },
  {
    "name": "mount",
    "path": "/mount",
    "description": "用于挂载Linux系统外的文件"
  },
  {
    "name": "mpstat",
    "path": "/mpstat",
    "description": "显示各个可用CPU的状态"
  },
  {
    "name": "mtools",
    "path": "/mtools",
    "description": "显示mtools支持的指令"
  },
  {
    "name": "mtr",
    "path": "/mtr",
    "description": "`mtr` 结合了 `traceroute` 和 `ping` 程序的功能，是一款简单的网络诊断工具"
  },
  {
    "name": "mv",
    "path": "/mv",
    "description": "用来对文件或目录重新命名"
  },
  {
    "name": "mysql",
    "path": "/mysql",
    "description": "MySQL服务器客户端工具"
  },
  {
    "name": "mysqladmin",
    "path": "/mysqladmin",
    "description": "MySQL服务器管理客户端"
  },
  {
    "name": "mysqldump",
    "path": "/mysqldump",
    "description": "MySQL数据库中备份工具"
  },
  {
    "name": "mysqlimport",
    "path": "/mysqlimport",
    "description": "为MySQL服务器用命令行方式导入数据"
  },
  {
    "name": "mysqlshow",
    "path": "/mysqlshow",
    "description": "显示MySQL中数据库相关信息"
  },
  {
    "name": "named-checkzone",
    "path": "/named-checkzone",
    "description": "使用 named-checkzone 可验证并转换区域文件，需指定区域名和文件名。"
  },
  {
    "name": "nano",
    "path": "/nano",
    "description": "字符终端文本编辑器"
  },
  {
    "name": "nc",
    "path": "/nc",
    "description": "nc是网络工具中的瑞士军刀"
  },
  {
    "name": "ncdu",
    "path": "/ncdu",
    "description": "磁盘使用情况的交互式查看工具，可视为 du 的增强版本"
  },
  {
    "name": "ncftp",
    "path": "/ncftp",
    "description": "是增强的的FTP工具"
  },
  {
    "name": "neofetch",
    "path": "/neofetch",
    "description": "显示带有发行徽标的系统信息的工具"
  },
  {
    "name": "nethogs",
    "path": "/nethogs",
    "description": "终端下的网络流量监控工具"
  },
  {
    "name": "netstat",
    "path": "/netstat",
    "description": "查看Linux中网络系统状态信息"
  },
  {
    "name": "newusers",
    "path": "/newusers",
    "description": "用于批处理的方式一次创建多个命令"
  },
  {
    "name": "nfsstat",
    "path": "/nfsstat",
    "description": "列出NFS客户端和服务器的工作状态"
  },
  {
    "name": "ngrep",
    "path": "/ngrep",
    "description": "方便的数据包匹配和显示工具"
  },
  {
    "name": "nice",
    "path": "/nice",
    "description": "调整程序执行的优先权等级"
  },
  {
    "name": "nisdomainname",
    "path": "/nisdomainname",
    "description": "显示主机NIS的域名"
  },
  {
    "name": "nl",
    "path": "/nl",
    "description": "为每一个文件添加行号。"
  },
  {
    "name": "nm",
    "path": "/nm",
    "description": "显示二进制目标文件的符号表"
  },
  {
    "name": "nmap",
    "path": "/nmap",
    "description": "网络探测和安全审核"
  },
  {
    "name": "nmcli",
    "path": "/nmcli",
    "description": "地址配置工具"
  },
  {
    "name": "nohup",
    "path": "/nohup",
    "description": "将程序以忽略挂起信号的方式运行起来"
  },
  {
    "name": "nologin",
    "path": "/nologin",
    "description": "拒绝用户登录系统"
  },
  {
    "name": "nproc",
    "path": "/nproc",
    "description": "打印可用的处理器单元数量。"
  },
  {
    "name": "nslookup",
    "path": "/nslookup",
    "description": "查询域名DNS信息的工具"
  },
  {
    "name": "nstat",
    "path": "/nstat",
    "description": "nstat 是一个简单的监视内核的 SNMP 计数器和网络接口状态的实用工具。"
  },
  {
    "name": "ntpdate",
    "path": "/ntpdate",
    "description": "使用网络计时协议（NTP）设置日期和时间"
  },
  {
    "name": "ntsysv",
    "path": "/ntsysv",
    "description": "集中管理系统的各种服务"
  },
  {
    "name": "objdump",
    "path": "/objdump",
    "description": "显示二进制文件信息"
  },
  {
    "name": "od",
    "path": "/od",
    "description": "输出文件的八进制、十六进制等格式编码的字节"
  },
  {
    "name": "openssl",
    "path": "/openssl",
    "description": "强大的安全套接字层密码库"
  },
  {
    "name": "pacman",
    "path": "/pacman",
    "description": "Arch Linux 系统及其衍生系统中默认使用的包管理器"
  },
  {
    "name": "parted",
    "path": "/parted",
    "description": "磁盘分区和分区大小调整工具"
  },
  {
    "name": "partprobe",
    "path": "/partprobe",
    "description": "不重启的情况下重读分区"
  },
  {
    "name": "passwd",
    "path": "/passwd",
    "description": "用于让用户可以更改自己的密码"
  },
  {
    "name": "paste",
    "path": "/paste",
    "description": "将多个文件按列队列合并"
  },
  {
    "name": "patch",
    "path": "/patch",
    "description": "为开放源代码软件安装补丁程序"
  },
  {
    "name": "pathchk",
    "path": "/pathchk",
    "description": "检查文件中不可移植的部分"
  },
  {
    "name": "perl",
    "path": "/perl",
    "description": "perl语言解释器"
  },
  {
    "name": "pfctl",
    "path": "/pfctl",
    "description": "PF防火墙的配置命令"
  },
  {
    "name": "pgrep",
    "path": "/pgrep",
    "description": "根据用户给出的信息在当前运行进程中查找并列出符合条件的进程ID（PID）"
  },
  {
    "name": "php",
    "path": "/php",
    "description": "PHP语言的命令行接口"
  },
  {
    "name": "pico",
    "path": "/pico",
    "description": "功能强大全屏幕的文本编辑器"
  },
  {
    "name": "pidof",
    "path": "/pidof",
    "description": "查找指定名称的进程的进程号ID号"
  },
  {
    "name": "pidstat",
    "path": "/pidstat",
    "description": "监控进程的系统资源占用情况"
  },
  {
    "name": "pigz",
    "path": "/pigz",
    "description": "可以用来解压缩文件，gzip的并行实现升级版"
  },
  {
    "name": "ping",
    "path": "/ping",
    "description": "测试主机之间网络的连通性(ipv4)"
  },
  {
    "name": "ping6",
    "path": "/ping6",
    "description": "测试主机之间网络的连通性(ipv6)"
  },
  {
    "name": "pip",
    "path": "/pip",
    "description": "Python 编程语言中的包管理器，用于安装和管理第三方 Python 模块"
  },
  {
    "name": "pkexec",
    "path": "/pkexec",
    "description": "以其他用户身份执行命令"
  },
  {
    "name": "pkill",
    "path": "/pkill",
    "description": "可以按照进程名杀死进程"
  },
  {
    "name": "pmap",
    "path": "/pmap",
    "description": "报告进程的内存映射关系"
  },
  {
    "name": "popd",
    "path": "/popd",
    "description": "从目录堆栈中删除目录。"
  },
  {
    "name": "poweroff",
    "path": "/poweroff",
    "description": "关闭Linux系统，关闭记录会被写入到/var/log/wtmp日志文件中"
  },
  {
    "name": "ppp-off",
    "path": "/ppp-off",
    "description": "关闭ppp连线"
  },
  {
    "name": "pr",
    "path": "/pr",
    "description": "将文本文件转换成适合打印的格式"
  },
  {
    "name": "printf",
    "path": "/printf",
    "description": "格式化并输出结果。"
  },
  {
    "name": "protoize",
    "path": "/protoize",
    "description": "GNU-C代码转换为ANSI-C代码"
  },
  {
    "name": "prtstat",
    "path": "/prtstat",
    "description": "显示进程信息"
  },
  {
    "name": "ps",
    "path": "/ps",
    "description": "报告当前系统的进程状态"
  },
  {
    "name": "pssh",
    "path": "/pssh",
    "description": "批量管理执行"
  },
  {
    "name": "pstack",
    "path": "/pstack",
    "description": "显示每个进程的栈跟踪"
  },
  {
    "name": "pstree",
    "path": "/pstree",
    "description": "以树状图的方式展现进程之间的派生关系"
  },
  {
    "name": "pushd",
    "path": "/pushd",
    "description": "将目录添加到目录堆栈顶部。"
  },
  {
    "name": "pv",
    "path": "/pv",
    "description": "显示当前在命令行执行的命令的进度信息，管道查看器"
  },
  {
    "name": "pvchange",
    "path": "/pvchange",
    "description": "修改物理卷属性"
  },
  {
    "name": "pvck",
    "path": "/pvck",
    "description": "检测物理卷的LVM元数据的一致性"
  },
  {
    "name": "pvcreate",
    "path": "/pvcreate",
    "description": "将物理硬盘分区初始化为物理卷"
  },
  {
    "name": "pvdisplay",
    "path": "/pvdisplay",
    "description": "显示物理卷的属性"
  },
  {
    "name": "pvremove",
    "path": "/pvremove",
    "description": "删除一个存在的物理卷"
  },
  {
    "name": "pvs",
    "path": "/pvs",
    "description": "输出物理卷信息报表"
  },
  {
    "name": "pvscan",
    "path": "/pvscan",
    "description": "扫描系统中所有硬盘的物理卷列表"
  },
  {
    "name": "pwck",
    "path": "/pwck",
    "description": "用来验证系统认证文件内容和格式的完整性"
  },
  {
    "name": "pwconv",
    "path": "/pwconv",
    "description": "用来开启用户的投影密码"
  },
  {
    "name": "pwd",
    "path": "/pwd",
    "description": "显示当前工作目录的绝对路径。"
  },
  {
    "name": "pwdx",
    "path": "/pwdx",
    "description": "用于显示指定进程的当前工作目录"
  },
  {
    "name": "pwunconv",
    "path": "/pwunconv",
    "description": "用来关闭用户的投影密码"
  },
  {
    "name": "quota",
    "path": "/quota",
    "description": "显示磁盘已使用的空间与限制"
  },
  {
    "name": "quotacheck",
    "path": "/quotacheck",
    "description": "检查磁盘的使用空间与限制"
  },
  {
    "name": "quotaoff",
    "path": "/quotaoff",
    "description": "关闭Linux内核中指定文件系统的磁盘配额功能"
  },
  {
    "name": "quotaon",
    "path": "/quotaon",
    "description": "激活Linux内核中指定文件系统的磁盘配额功能"
  },
  {
    "name": "rcconf",
    "path": "/rcconf",
    "description": "Debian Linux下的运行等级服务配置工具"
  },
  {
    "name": "rcp",
    "path": "/rcp",
    "description": "使在两台Linux主机之间的文件复制操作更简单"
  },
  {
    "name": "read",
    "path": "/read",
    "description": "从键盘读取变量值"
  },
  {
    "name": "readelf",
    "path": "/readelf",
    "description": "用于显示elf格式文件的信息"
  },
  {
    "name": "readonly",
    "path": "/readonly",
    "description": "标记shell变量或函数为只读"
  },
  {
    "name": "realpath",
    "path": "/realpath",
    "description": "解析并规范化文件路径，返回绝对路径。"
  },
  {
    "name": "reboot",
    "path": "/reboot",
    "description": "重新启动正在运行的Linux操作系统"
  },
  {
    "name": "reject",
    "path": "/reject",
    "description": "指示打印系统拒绝发往指定目标打印机的打印任务"
  },
  {
    "name": "rename",
    "path": "/rename",
    "description": "用字符串替换的方式批量改变文件名"
  },
  {
    "name": "renice",
    "path": "/renice",
    "description": "修改正在运行的进程的调度优先级"
  },
  {
    "name": "reposync",
    "path": "/reposync",
    "description": "同步yum存储库到本地目录"
  },
  {
    "name": "repquota",
    "path": "/repquota",
    "description": "报表的格式输出磁盘空间限制的状态"
  },
  {
    "name": "resize",
    "path": "/resize",
    "description": "命令设置终端机视窗的大小"
  },
  {
    "name": "restore",
    "path": "/restore",
    "description": "所进行的操作和dump指令相反"
  },
  {
    "name": "restorecon",
    "path": "/restorecon",
    "description": "恢复文件的安全上下文"
  },
  {
    "name": "return",
    "path": "/return",
    "description": "从函数中退出并返回数值。"
  },
  {
    "name": "rev",
    "path": "/rev",
    "description": "将文件内容以字符为单位反序输出"
  },
  {
    "name": "rexec",
    "path": "/rexec",
    "description": "远程执行Linux系统下命令"
  },
  {
    "name": "rlogin",
    "path": "/rlogin",
    "description": "从当前终端登录到远程Linux主机"
  },
  {
    "name": "rm",
    "path": "/rm",
    "description": "用于删除给定的文件和目录"
  },
  {
    "name": "rmdir",
    "path": "/rmdir",
    "description": "用来删除空目录"
  },
  {
    "name": "rmmod",
    "path": "/rmmod",
    "description": "从运行的内核中移除指定的内核模块"
  },
  {
    "name": "route",
    "path": "/route",
    "description": "显示并设置Linux中静态路由表"
  },
  {
    "name": "rpm",
    "path": "/rpm",
    "description": "RPM软件包的管理工具"
  },
  {
    "name": "rpm2cpio",
    "path": "/rpm2cpio",
    "description": "将RPM软件包转换为cpio格式的文件"
  },
  {
    "name": "rpmbuild",
    "path": "/rpmbuild",
    "description": "创建RPM的二进制软件包和源码软件包"
  },
  {
    "name": "rpmdb",
    "path": "/rpmdb",
    "description": "初始化和重建RPM数据库"
  },
  {
    "name": "rpmquery",
    "path": "/rpmquery",
    "description": "从RPM数据库中查询软件包信息"
  },
  {
    "name": "rpmsign",
    "path": "/rpmsign",
    "description": "使用RPM软件包的签名管理工具"
  },
  {
    "name": "rpmverify",
    "path": "/rpmverify",
    "description": "验证已安装的RPM软件包的正确性"
  },
  {
    "name": "rsh",
    "path": "/rsh",
    "description": "连接远程主机并执行命令"
  },
  {
    "name": "rsync",
    "path": "/rsync",
    "description": "远程数据同步工具"
  },
  {
    "name": "runlevel",
    "path": "/runlevel",
    "description": "打印当前Linux系统的运行等级"
  },
  {
    "name": "sar",
    "path": "/sar",
    "description": "系统运行状态统计工具"
  },
  {
    "name": "scp",
    "path": "/scp",
    "description": "加密的方式在本地主机和远程主机之间复制文件"
  },
  {
    "name": "screen",
    "path": "/screen",
    "description": "用于命令行终端切换"
  },
  {
    "name": "script",
    "path": "/script",
    "description": "记录终端会话的所有操作"
  },
  {
    "name": "scriptreplay",
    "path": "/scriptreplay",
    "description": "重新播放终端会话的所有操作"
  },
  {
    "name": "sed",
    "path": "/sed",
    "description": "功能强大的流式文本编辑器"
  },
  {
    "name": "seinfo",
    "path": "/seinfo",
    "description": "查询SELinux的策略提供多少相关规则"
  },
  {
    "name": "semanage",
    "path": "/semanage",
    "description": "默认目录的安全上下文查询与修改"
  },
  {
    "name": "sendmail",
    "path": "/sendmail",
    "description": "著名电子邮件服务器"
  },
  {
    "name": "seq",
    "path": "/seq",
    "description": "以指定增量从首数开始打印数字到尾数"
  },
  {
    "name": "service",
    "path": "/service",
    "description": "控制系统服务的实用工具"
  },
  {
    "name": "sesearch",
    "path": "/sesearch",
    "description": "查询SELinux策略的规则详情"
  },
  {
    "name": "set",
    "path": "/set",
    "description": "显示或设置shell特性及shell变量"
  },
  {
    "name": "setfacl",
    "path": "/setfacl",
    "description": "设置文件访问控制列表"
  },
  {
    "name": "setpci",
    "path": "/setpci",
    "description": "查询和配置PCI设备的使用工具"
  },
  {
    "name": "setsebool",
    "path": "/setsebool",
    "description": "修改SElinux策略内各项规则的布尔值"
  },
  {
    "name": "setsid",
    "path": "/setsid",
    "description": "在新的会话中运行程序"
  },
  {
    "name": "sftp-server",
    "path": "/sftp-server",
    "description": "sftp协议的服务器端程序"
  },
  {
    "name": "sftp",
    "path": "/sftp",
    "description": "交互式的文件传输程序"
  },
  {
    "name": "sh",
    "path": "/sh",
    "description": "shell命令解释器"
  },
  {
    "name": "sha256sum",
    "path": "/sha256sum",
    "description": "用于计算文件的 SHA-256 哈希值"
  },
  {
    "name": "shift",
    "path": "/shift",
    "description": "移动位置参数。"
  },
  {
    "name": "shopt",
    "path": "/shopt",
    "description": "显示和设置shell操作选项"
  },
  {
    "name": "showmount",
    "path": "/showmount",
    "description": "显示NFS服务器加载的信息"
  },
  {
    "name": "shuf",
    "path": "/shuf",
    "description": "产生随机的排列。"
  },
  {
    "name": "shutdown",
    "path": "/shutdown",
    "description": "用来执行系统关机的命令"
  },
  {
    "name": "skill",
    "path": "/skill",
    "description": "向选定的进程发送信号冻结进程"
  },
  {
    "name": "slabtop",
    "path": "/slabtop",
    "description": "实时显示内核slab内存缓存信息"
  },
  {
    "name": "sleep",
    "path": "/sleep",
    "description": "将目前动作延迟一段时间"
  },
  {
    "name": "slocate",
    "path": "/slocate",
    "description": "命令查找文件或目录"
  },
  {
    "name": "smartmontools",
    "path": "/smartmontools",
    "description": "Smartmontools 是一种硬盘检测工具，通过控制和管理硬盘的SMART（Self Monitoring Analysis and Reporting Technology，自动检测分析及报告技术）技术来实现的"
  },
  {
    "name": "smbclient",
    "path": "/smbclient",
    "description": "交互方式访问samba服务器"
  },
  {
    "name": "smbpasswd",
    "path": "/smbpasswd",
    "description": "samba用户和密码管理工具"
  },
  {
    "name": "sort",
    "path": "/sort",
    "description": "对文本文件中所有行进行排序。"
  },
  {
    "name": "sosreport",
    "path": "/sosreport",
    "description": "收集系统配置和诊断信息"
  },
  {
    "name": "source",
    "path": "/source",
    "description": "在当前Shell环境中从指定文件读取和执行命令。"
  },
  {
    "name": "speedtest-cli",
    "path": "/speedtest-cli",
    "description": "命令行下测试服务器外网速度"
  },
  {
    "name": "spell",
    "path": "/spell",
    "description": "对文件进行拼写检查"
  },
  {
    "name": "split",
    "path": "/split",
    "description": "分割任意大小的文件"
  },
  {
    "name": "squid",
    "path": "/squid",
    "description": "squid服务器守护进程"
  },
  {
    "name": "squidclient",
    "path": "/squidclient",
    "description": "squid服务器的客户端管理工具"
  },
  {
    "name": "ss",
    "path": "/ss",
    "description": "比 netstat 好用的socket统计信息，iproute2 包附带的另一个工具，允许你查询 socket 的有关统计信息"
  },
  {
    "name": "ssh-add",
    "path": "/ssh-add",
    "description": "把专用密钥添加到ssh-agent的高速缓存中"
  },
  {
    "name": "ssh-agent",
    "path": "/ssh-agent",
    "description": "ssh密钥管理器"
  },
  {
    "name": "ssh-copy-id",
    "path": "/ssh-copy-id",
    "description": "把本地的ssh公钥文件安装到远程主机对应的账户下"
  },
  {
    "name": "ssh-keygen",
    "path": "/ssh-keygen",
    "description": "为ssh生成、管理和转换认证密钥"
  },
  {
    "name": "ssh-keyscan",
    "path": "/ssh-keyscan",
    "description": "收集主机公钥的使用工具"
  },
  {
    "name": "ssh",
    "path": "/ssh",
    "description": "openssh套件中的客户端连接工具"
  },
  {
    "name": "sshd",
    "path": "/sshd",
    "description": "openssh软件套件中的服务器守护进程"
  },
  {
    "name": "sshpass",
    "path": "/sshpass",
    "description": "免交互 SSH 登录工具。"
  },
  {
    "name": "startx",
    "path": "/startx",
    "description": "用来启动X Window"
  },
  {
    "name": "stat",
    "path": "/stat",
    "description": "用于显示文件的状态信息"
  },
  {
    "name": "strace",
    "path": "/strace",
    "description": "跟踪系统调用和信号"
  },
  {
    "name": "strings",
    "path": "/strings",
    "description": "在对象文件或二进制文件中查找可打印的字符串"
  },
  {
    "name": "stty",
    "path": "/stty",
    "description": "修改终端命令行的相关设置"
  },
  {
    "name": "su",
    "path": "/su",
    "description": "用于切换当前用户身份到其他用户身份"
  },
  {
    "name": "sudo",
    "path": "/sudo",
    "description": "以其他身份来执行命令"
  },
  {
    "name": "sum",
    "path": "/sum",
    "description": "计算文件的校验码和显示块数"
  },
  {
    "name": "supervisord",
    "path": "/supervisord",
    "description": "配置后台服务/常驻进程的进程管家工具"
  },
  {
    "name": "suspend",
    "path": "/suspend",
    "description": "挂起shell的执行。"
  },
  {
    "name": "swapoff",
    "path": "/swapoff",
    "description": "关闭指定的交换空间"
  },
  {
    "name": "swapon",
    "path": "/swapon",
    "description": "激活Linux系统中交换空间"
  },
  {
    "name": "sync",
    "path": "/sync",
    "description": "用于强制被改变的内容立刻写入磁盘"
  },
  {
    "name": "sysctl",
    "path": "/sysctl",
    "description": "时动态地修改内核的运行参数"
  },
  {
    "name": "syslog",
    "path": "/syslog",
    "description": "系统默认的日志守护进程"
  },
  {
    "name": "systemctl",
    "path": "/systemctl",
    "description": "系统服务管理器指令"
  },
  {
    "name": "systool",
    "path": "/systool",
    "description": "显示基于总线、类和拓扑显示系统中设备的信息"
  },
  {
    "name": "tac",
    "path": "/tac",
    "description": "连接多个文件并以行为单位反向打印到标准输出。"
  },
  {
    "name": "tail",
    "path": "/tail",
    "description": "在屏幕上显示指定文件的末尾若干行"
  },
  {
    "name": "tailf",
    "path": "/tailf",
    "description": "在屏幕上显示指定文件的末尾若干行内容，通常用于日志文件的跟踪输出"
  },
  {
    "name": "talk",
    "path": "/talk",
    "description": "让用户和其他用户聊天"
  },
  {
    "name": "tar",
    "path": "/tar",
    "description": "将许多文件一起保存至一个单独的磁带或磁盘归档，并能从归档中单独还原所需文件。"
  },
  {
    "name": "tcpdump",
    "path": "/tcpdump",
    "description": "一款sniffer工具，是Linux上的抓包工具，嗅探器"
  },
  {
    "name": "tcpreplay",
    "path": "/tcpreplay",
    "description": "将保存在 PCAP 文件包重新发送，用于性能或者功能测试"
  },
  {
    "name": "tee",
    "path": "/tee",
    "description": "从标准输入读取数据并重定向到标准输出和文件。"
  },
  {
    "name": "telinit",
    "path": "/telinit",
    "description": "切换当前正在运行系统的运行等级"
  },
  {
    "name": "telnet",
    "path": "/telnet",
    "description": "登录远程主机和管理(测试ip端口是否连通)"
  },
  {
    "name": "tempfile",
    "path": "/tempfile",
    "description": "shell中给临时文件命名"
  },
  {
    "name": "test",
    "path": "/test",
    "description": "执行条件表达式。"
  },
  {
    "name": "tftp",
    "path": "/tftp",
    "description": "在本机和tftp服务器之间使用TFTP协议传输文件"
  },
  {
    "name": "time",
    "path": "/time",
    "description": "统计给定命令所花费的总时间"
  },
  {
    "name": "timedatectl",
    "path": "/timedatectl",
    "description": "用于在 Linux 中设置或查询系统时间、日期和时区等配置。"
  },
  {
    "name": "times",
    "path": "/times",
    "description": "显示进程累计时间。"
  },
  {
    "name": "tload",
    "path": "/tload",
    "description": "显示系统负载状况"
  },
  {
    "name": "tmux",
    "path": "/tmux",
    "description": "Tmux是一个优秀的终端复用软件，类似GNU Screen，但来自于OpenBSD，采用BSD授权"
  },
  {
    "name": "top",
    "path": "/top",
    "description": "显示或管理执行中的程序"
  },
  {
    "name": "touch",
    "path": "/touch",
    "description": "创建新的空文件"
  },
  {
    "name": "tput",
    "path": "/tput",
    "description": "通过terminfo数据库对终端会话进行初始化和操作"
  },
  {
    "name": "tr",
    "path": "/tr",
    "description": "将字符进行替换压缩和删除"
  },
  {
    "name": "tracepath",
    "path": "/tracepath",
    "description": "追踪目的主机经过的路由信息"
  },
  {
    "name": "traceroute",
    "path": "/traceroute",
    "description": "显示数据包到主机间的路径"
  },
  {
    "name": "trap",
    "path": "/trap",
    "description": "捕捉信号和其他事件并执行命令。"
  },
  {
    "name": "tree",
    "path": "/tree",
    "description": "树状图列出目录的内容"
  },
  {
    "name": "true",
    "path": "/true",
    "description": "返回状态为成功。"
  },
  {
    "name": "tty",
    "path": "/tty",
    "description": "显示连接到当前标准输入的终端设备文件名"
  },
  {
    "name": "type",
    "path": "/type",
    "description": "显示指定命令的类型。"
  },
  {
    "name": "ufw",
    "path": "/ufw",
    "description": "  ubuntu防火墙管理工具"
  },
  {
    "name": "ulimit",
    "path": "/ulimit",
    "description": "控制shell程序的资源"
  },
  {
    "name": "umask",
    "path": "/umask",
    "description": "显示或设置创建文件的权限掩码。"
  },
  {
    "name": "umount",
    "path": "/umount",
    "description": "用于卸载已经加载的文件系统"
  },
  {
    "name": "unalias",
    "path": "/unalias",
    "description": "删除由alias设置的别名"
  },
  {
    "name": "uname",
    "path": "/uname",
    "description": "打印系统信息。"
  },
  {
    "name": "unarj",
    "path": "/unarj",
    "description": "解压缩由arj命令创建的压缩包"
  },
  {
    "name": "uncompress",
    "path": "/uncompress",
    "description": "用来解压.Z文件"
  },
  {
    "name": "unexpand",
    "path": "/unexpand",
    "description": "将文件的空白字符转换为制表符"
  },
  {
    "name": "uniq",
    "path": "/uniq",
    "description": "显示或忽略重复的行。"
  },
  {
    "name": "unlink",
    "path": "/unlink",
    "description": "系统调用函数unlink去删除指定的文件"
  },
  {
    "name": "unprotoize",
    "path": "/unprotoize",
    "description": "删除C语言源代码文件中的函数原型"
  },
  {
    "name": "unrar",
    "path": "/unrar",
    "description": "解压rar文件命令，从 rar 压缩包中提取文件"
  },
  {
    "name": "unset",
    "path": "/unset",
    "description": "删除指定的shell变量或函数。"
  },
  {
    "name": "unzip",
    "path": "/unzip",
    "description": "用于解压缩由zip命令压缩的压缩包"
  },
  {
    "name": "updatedb",
    "path": "/updatedb",
    "description": "创建或更新slocate命令所必需的数据库文件"
  },
  {
    "name": "uptime",
    "path": "/uptime",
    "description": "查看Linux系统负载信息"
  },
  {
    "name": "useradd",
    "path": "/useradd",
    "description": "创建的新的系统用户"
  },
  {
    "name": "userdel",
    "path": "/userdel",
    "description": "用于删除给定的用户以及与用户相关的文件"
  },
  {
    "name": "usermod",
    "path": "/usermod",
    "description": "用于修改用户的基本信息"
  },
  {
    "name": "usernetctl",
    "path": "/usernetctl",
    "description": "被允许时操作指定的网络接口"
  },
  {
    "name": "users",
    "path": "/users",
    "description": "打印当前主机所有登陆用户的名称。"
  },
  {
    "name": "uucico",
    "path": "/uucico",
    "description": "UUCP文件传输服务程序"
  },
  {
    "name": "uupick",
    "path": "/uupick",
    "description": "命令处理传送进来的文件"
  },
  {
    "name": "uuto",
    "path": "/uuto",
    "description": "将文件传送到远端的UUCP主机"
  },
  {
    "name": "vdfuse",
    "path": "/vdfuse",
    "description": "VirtualBox软件挂载VDI分区文件工具"
  },
  {
    "name": "vgchange",
    "path": "/vgchange",
    "description": "修改卷组属性"
  },
  {
    "name": "vgconvert",
    "path": "/vgconvert",
    "description": "转换卷组元数据格式"
  },
  {
    "name": "vgcreate",
    "path": "/vgcreate",
    "description": "用于创建LVM卷组"
  },
  {
    "name": "vgdisplay",
    "path": "/vgdisplay",
    "description": "显示LVM卷组的信息"
  },
  {
    "name": "vgextend",
    "path": "/vgextend",
    "description": "向卷组中添加物理卷"
  },
  {
    "name": "vgreduce",
    "path": "/vgreduce",
    "description": "从卷组中删除物理卷"
  },
  {
    "name": "vgremove",
    "path": "/vgremove",
    "description": "用于用户删除LVM卷组"
  },
  {
    "name": "vgrename",
    "path": "/vgrename",
    "description": "使用vgrename命令可以重命名卷组的名称"
  },
  {
    "name": "vgscan",
    "path": "/vgscan",
    "description": "扫描并显示系统中的卷组"
  },
  {
    "name": "vi",
    "path": "/vi",
    "description": "功能强大的纯文本编辑器"
  },
  {
    "name": "vmstat",
    "path": "/vmstat",
    "description": "显示虚拟内存状态"
  },
  {
    "name": "volname",
    "path": "/volname",
    "description": "显示指定的ISO-9660格式的设备的卷名称"
  },
  {
    "name": "w",
    "path": "/w",
    "description": "显示目前登入系统的用户信息"
  },
  {
    "name": "wait",
    "path": "/wait",
    "description": "等待进程执行完后返回"
  },
  {
    "name": "wall",
    "path": "/wall",
    "description": "向系统当前所有打开的终端上输出信息"
  },
  {
    "name": "watch",
    "path": "/watch",
    "description": "可以将命令的输出结果输出到标准输出设备，多用于周期性执行命令/定时执行命令"
  },
  {
    "name": "wc",
    "path": "/wc",
    "description": "统计文件的字节数、字数、行数"
  },
  {
    "name": "wget",
    "path": "/wget",
    "description": "Linux系统下载文件工具"
  },
  {
    "name": "whatis",
    "path": "/whatis",
    "description": "查询一个命令执行什么功能"
  },
  {
    "name": "whereis",
    "path": "/whereis",
    "description": "查找二进制程序、代码等相关文件路径"
  },
  {
    "name": "which",
    "path": "/which",
    "description": "查找并显示给定命令的绝对路径"
  },
  {
    "name": "who",
    "path": "/who",
    "description": "显示当前所有登陆用户的信息。"
  },
  {
    "name": "whoami",
    "path": "/whoami",
    "description": "打印当前有效的用户ID对应的名称"
  },
  {
    "name": "write",
    "path": "/write",
    "description": "向指定登录用户终端上发送信息"
  },
  {
    "name": "xargs",
    "path": "/xargs",
    "description": "给其他命令传递参数的一个过滤器"
  },
  {
    "name": "xauth",
    "path": "/xauth",
    "description": "显示和编辑被用于连接X服务器的认证信息"
  },
  {
    "name": "xclip",
    "path": "/xclip",
    "description": "管理 X 粘贴板"
  },
  {
    "name": "xhost",
    "path": "/xhost",
    "description": "制哪些X客户端能够在X服务器上显示"
  },
  {
    "name": "xinit",
    "path": "/xinit",
    "description": "是Linux下X-Window系统的初始化程序"
  },
  {
    "name": "xlsatoms",
    "path": "/xlsatoms",
    "description": "列出X服务器内部所有定义的原子成分"
  },
  {
    "name": "xlsclients",
    "path": "/xlsclients",
    "description": "列出显示器中的客户端应用程序"
  },
  {
    "name": "xlsfonts",
    "path": "/xlsfonts",
    "description": "列出X Server使用的字体"
  },
  {
    "name": "xrandr",
    "path": "/xrandr",
    "description": "X 窗口系统配置管理工具"
  },
  {
    "name": "xset",
    "path": "/xset",
    "description": "设置X-Window系统中的用户爱好的实用工具"
  },
  {
    "name": "xz",
    "path": "/xz",
    "description": "POSIX 平台开发具有高压缩率的工具"
  },
  {
    "name": "yes",
    "path": "/yes",
    "description": "重复打印指定字符串"
  },
  {
    "name": "ypdomainname",
    "path": "/ypdomainname",
    "description": "显示主机的NIS的域名"
  },
  {
    "name": "yum",
    "path": "/yum",
    "description": "基于RPM的软件包管理器"
  },
  {
    "name": "zcat",
    "path": "/zcat",
    "description": "显示压缩包中文件的内容"
  },
  {
    "name": "zfore",
    "path": "/zfore",
    "description": "强制为gzip格式的压缩文件添加.gz后缀"
  },
  {
    "name": "zip",
    "path": "/zip",
    "description": "可以用来解压缩文件"
  },
  {
    "name": "zipinfo",
    "path": "/zipinfo",
    "description": "用来列出压缩文件信息"
  },
  {
    "name": "zipsplit",
    "path": "/zipsplit",
    "description": "将较大的zip压缩包分割成各个较小的压缩包"
  },
  {
    "name": "znew",
    "path": "/znew",
    "description": "将.Z压缩包重新转化为gzip命令压缩的.gz压缩包"
  }
]